soil_moisture_prediction/.gitignore
soil_moisture_prediction/__init__.py
soil_moisture_prediction/__version__.py
soil_moisture_prediction/area_geometry.py
soil_moisture_prediction/create_usage_information.py
soil_moisture_prediction/input_data.py
soil_moisture_prediction/input_file_parser.py
soil_moisture_prediction/plot_functions.py
soil_moisture_prediction/pydantic_models.py
soil_moisture_prediction/random_forest_model.py
soil_moisture_prediction/smp_cli.py
soil_moisture_prediction/streams.py
soil_moisture_prediction/test_data/crn_soil-moisture.csv
soil_moisture_prediction/test_data/parameters.json
soil_moisture_prediction/test_data/predictor_1.csv
soil_moisture_prediction/test_data/predictor_1_no_deviation.csv
soil_moisture_prediction/test_data/predictor_1_to_many_columns.csv
soil_moisture_prediction/test_data/predictor_2.csv
soil_moisture_prediction/test_data/predictor_3.csv
soil_moisture_prediction/test_data/predictor_4.csv
soil_moisture_prediction/test_data/predictor_4_nan_in_training.csv
soil_moisture_prediction/test_data/predictor_4_wrong_nan.csv
soil_moisture_prediction/usage_information.txt
soil_moisture_prediction-0.0.43.dist-info/METADATA
soil_moisture_prediction-0.0.43.dist-info/WHEEL
soil_moisture_prediction-0.0.43.dist-info/entry_points.txt
soil_moisture_prediction-0.0.43.dist-info/licenses/LICENSE
soil_moisture_prediction-0.0.43.dist-info/RECORD
