Metadata-Version: 2.4
Name: soil-moisture-prediction
Version: 0.0.43
Summary: Predicts soil moisture from cosmic ray neutron sensor data using a random forest model
License: EUPL 1.2
License-File: LICENSE
Author: Segolene Dega
Author-email: segolene.dega@ufz.de
Requires-Python: >=3.10,<4.0
Classifier: License :: Other/Proprietary License
Classifier: Programming Language :: Python :: 3
Classifier: Programming Language :: Python :: 3.10
Classifier: Programming Language :: Python :: 3.11
Classifier: Programming Language :: Python :: 3.12
Classifier: Programming Language :: Python :: 3.13
Classifier: Programming Language :: Python :: 3.14
Requires-Dist: certifi (>=2025.4.26,<2026.0.0)
Requires-Dist: charset-normalizer (>=3.4.2,<4.0.0)
Requires-Dist: contourpy (>=1.3.2,<2.0.0)
Requires-Dist: cycler (>=0.12.1,<0.13.0)
Requires-Dist: dask (>=2025.4.1,<2026.0.0)
Requires-Dist: exceptiongroup (>=1.2.2,<2.0.0)
Requires-Dist: flake8 (>=7.2.0,<8.0.0)
Requires-Dist: fonttools (>=4.57.0,<5.0.0)
Requires-Dist: fsspec (>=2025.3.2,<2026.0.0)
Requires-Dist: h5netcdf (>=1.6.1,<2.0.0)
Requires-Dist: importlib-metadata (>=8.7.0,<9.0.0)
Requires-Dist: importlib-resources (>=6.5.2,<7.0.0)
Requires-Dist: iniconfig (>=2.1.0,<3.0.0)
Requires-Dist: isort (>=6.0.1,<7.0.0)
Requires-Dist: joblib (>=1.5.0,<2.0.0)
Requires-Dist: kiwisolver (>=1.4.8,<2.0.0)
Requires-Dist: lxml (>=5.4.0,<6.0.0)
Requires-Dist: matplotlib (>=3.10.3,<4.0.0)
Requires-Dist: mypy-extensions (>=1.1.0,<2.0.0)
Requires-Dist: numpy (>=2.2.5,<3.0.0)
Requires-Dist: owslib (>=0.33.0,<0.34.0)
Requires-Dist: packaging (>=25.0,<26.0)
Requires-Dist: pandas (>=2.2.3,<3.0.0)
Requires-Dist: pillow (>=11.2.1,<12.0.0)
Requires-Dist: platformdirs (>=4.3.8,<5.0.0)
Requires-Dist: pluggy (==1.5.0)
Requires-Dist: pydantic (>=2.11.4,<3.0.0)
Requires-Dist: pyparsing (>=3.2.3,<4.0.0)
Requires-Dist: pyproj (>=3.6.1,<4.0.0)
Requires-Dist: pytest (>=8.3.5,<9.0.0)
Requires-Dist: python-dateutil (>=2.9.0.post0,<3.0.0)
Requires-Dist: pytz (>=2025.2,<2026.0)
Requires-Dist: rasterio (>=1.3.10,<2.0.0)
Requires-Dist: scikit-learn (>=1.6.1,<2.0.0)
Requires-Dist: scipy (>=1.15.3,<2.0.0)
Requires-Dist: seaborn (>=0.13.2,<0.14.0)
Requires-Dist: six (>=1.17.0,<2.0.0)
Requires-Dist: snowballstemmer (>=3.0.0.1,<4.0.0.0)
Requires-Dist: threadpoolctl (>=3.6.0,<4.0.0)
Requires-Dist: toml (>=0.10.2,<0.11.0)
Requires-Dist: tomli (>=2.2.1,<3.0.0)
Requires-Dist: typing-extensions (>=4.13.2,<5.0.0)
Requires-Dist: tzdata (>=2025.2,<2026.0)
Requires-Dist: urllib3 (>=1.26.0,<2.0.0)
Requires-Dist: wradlib (>=2.4.0,<3.0.0)
Requires-Dist: xarray (>=2025.4.0,<2026.0.0)
Requires-Dist: xradar (>=0.9.0,<0.10.0)
Requires-Dist: xycmap (==1.0.1)
Requires-Dist: zipp (>=3.21.0,<4.0.0)
